{
  "updated_at": "2025-11-11T05:38:34.260Z",
  "meta": {
    "included_ids": [
      "bitcoin",
      "ethereum",
      "tether",
      "binancecoin",
      "solana",
      "ripple",
      "usd-coin",
      "staked-ether",
      "cardano",
      "dogecoin",
      "avalanche-2",
      "tron",
      "shiba-inu",
      "wrapped-bitcoin",
      "polkadot",
      "chainlink",
      "bitcoin-cash",
      "uniswap",
      "litecoin",
      "internet-computer",
      "dai",
      "near",
      "ethereum-classic",
      "filecoin",
      "aptos",
      "leo-token",
      "stellar",
      "okb",
      "vechain",
      "render-token",
      "monero",
      "arbitrum",
      "fantom",
      "the-graph",
      "immutable-x",
      "maker",
      "kaspa",
      "gala",
      "optimism",
      "frax",
      "sei-network",
      "algorand",
      "flow",
      "thorchain",
      "conflux-token",
      "mina-protocol",
      "worldcoin-wld",
      "polygon-ecosystem-token",
      "bonk",
      "book-of-meme",
      "official-trump",
      "streamflow",
      "pudgy-penguins",
      "just-a-chill-guy",
      "goatseus-maximus"
    ],
    "wallet_resolved": [
      {
        "raw": "worldcoin",
        "resolved": "worldcoin-wld",
        "via": "override"
      },
      {
        "raw": "pol",
        "resolved": "polygon-ecosystem-token",
        "via": "override"
      },
      {
        "raw": "bonk",
        "resolved": "bonk",
        "via": "id"
      },
      {
        "raw": "bome",
        "resolved": "book-of-meme",
        "via": "override"
      },
      {
        "raw": "official-trump",
        "resolved": "official-trump",
        "via": "id"
      },
      {
        "raw": "streamflow",
        "resolved": "streamflow",
        "via": "id"
      },
      {
        "raw": "pengu",
        "resolved": "pudgy-penguins",
        "via": "override"
      },
      {
        "raw": "just-a-chill-guy",
        "resolved": "just-a-chill-guy",
        "via": "id"
      },
      {
        "raw": "goatseus-maximus",
        "resolved": "goatseus-maximus",
        "via": "id"
      },
      {
        "raw": "optimism",
        "resolved": "optimism",
        "via": "id"
      },
      {
        "raw": "solana",
        "resolved": "solana",
        "via": "id"
      },
      {
        "raw": "ripple",
        "resolved": "ripple",
        "via": "id"
      }
    ],
    "missing": [],
    "ambiguous": []
  },
  "assets": {
    "BTC": {
      "usd": 105289,
      "change_24h": -0.8039117386076473,
      "change_7d": -1.3604630329785838,
      "market_cap": 2100334374062,
      "id": "bitcoin",
      "name": "Bitcoin",
      "source": "coingecko"
    },
    "ETH": {
      "usd": 3549.97,
      "change_24h": -1.3780513260914735,
      "change_7d": -2.0026402253350715,
      "market_cap": 428270191385,
      "id": "ethereum",
      "name": "Ethereum",
      "source": "coingecko"
    },
    "USDT": {
      "usd": 0.999657,
      "change_24h": -0.015867938744994245,
      "change_7d": -0.030947115380585095,
      "market_cap": 183474455220,
      "id": "tether",
      "name": "Tether",
      "source": "coingecko"
    },
    "XRP": {
      "usd": 2.48,
      "change_24h": 1.4352507029910624,
      "change_7d": 6.167379435022408,
      "market_cap": 149406809375,
      "id": "ripple",
      "name": "XRP",
      "source": "coingecko"
    },
    "BNB": {
      "usd": 982.52,
      "change_24h": -2.175786843495826,
      "change_7d": -0.6135081738728491,
      "market_cap": 135419074791,
      "id": "binancecoin",
      "name": "BNB",
      "source": "coingecko"
    },
    "SOL": {
      "usd": 165.48,
      "change_24h": -1.0875809948553468,
      "change_7d": -0.9734515246673496,
      "market_cap": 91765047301,
      "id": "solana",
      "name": "Solana",
      "source": "coingecko"
    },
    "USDC": {
      "usd": 0.9999,
      "change_24h": 0.019723891399271137,
      "change_7d": 0.009469052627101423,
      "market_cap": 76099719833,
      "id": "usd-coin",
      "name": "USDC",
      "source": "coingecko"
    },
    "STETH": {
      "usd": 3547.35,
      "change_24h": -1.354311131876257,
      "change_7d": -2.074257641876067,
      "market_cap": 30721829984,
      "id": "staked-ether",
      "name": "Lido Staked Ether",
      "source": "coingecko"
    },
    "TRX": {
      "usd": 0.296408,
      "change_24h": 0.8717276305797615,
      "change_7d": 4.273139244901965,
      "market_cap": 28072587146,
      "id": "tron",
      "name": "TRON",
      "source": "coingecko"
    },
    "DOGE": {
      "usd": 0.178489,
      "change_24h": -1.230594500553309,
      "change_7d": 5.154897187479909,
      "market_cap": 27093516881,
      "id": "dogecoin",
      "name": "Dogecoin",
      "source": "coingecko"
    },
    "ADA": {
      "usd": 0.584779,
      "change_24h": -0.1751357262314644,
      "change_7d": 4.390557515728106,
      "market_cap": 21411606856,
      "id": "cardano",
      "name": "Cardano",
      "source": "coingecko"
    },
    "WBTC": {
      "usd": 105105,
      "change_24h": -0.8786356234910561,
      "change_7d": -1.5565651791316706,
      "market_cap": 13329670947,
      "id": "wrapped-bitcoin",
      "name": "Wrapped Bitcoin",
      "source": "coingecko"
    },
    "LINK": {
      "usd": 16.2,
      "change_24h": -0.20804778134875207,
      "change_7d": 6.1792467953872885,
      "market_cap": 11310063167,
      "id": "chainlink",
      "name": "Chainlink",
      "source": "coingecko"
    },
    "BCH": {
      "usd": 523.03,
      "change_24h": 4.022068087644609,
      "change_7d": 2.4652248708997333,
      "market_cap": 10446116640,
      "id": "bitcoin-cash",
      "name": "Bitcoin Cash",
      "source": "coingecko"
    },
    "XLM": {
      "usd": 0.294762,
      "change_24h": 0.5823286783878452,
      "change_7d": 4.106861043343966,
      "market_cap": 9463367429,
      "id": "stellar",
      "name": "Stellar",
      "source": "coingecko"
    },
    "LEO": {
      "usd": 9.24,
      "change_24h": -0.24143192624123633,
      "change_7d": -3.5156368417671744,
      "market_cap": 8529116307,
      "id": "leo-token",
      "name": "LEO Token",
      "source": "coingecko"
    },
    "LTC": {
      "usd": 103.65,
      "change_24h": -4.20236463175566,
      "change_7d": 15.582334048323974,
      "market_cap": 7948464704,
      "id": "litecoin",
      "name": "Litecoin",
      "source": "coingecko"
    },
    "AVAX": {
      "usd": 17.84,
      "change_24h": -0.6062849259907721,
      "change_7d": 5.421243029295909,
      "market_cap": 7633545325,
      "id": "avalanche-2",
      "name": "Avalanche",
      "source": "coingecko"
    },
    "XMR": {
      "usd": 374.73,
      "change_24h": -11.959028759346154,
      "change_7d": 8.551610678074672,
      "market_cap": 6903676836,
      "id": "monero",
      "name": "Monero",
      "source": "coingecko"
    },
    "SHIB": {
      "usd": 0.00000997,
      "change_24h": -0.9742616943853073,
      "change_7d": 7.688971875223224,
      "market_cap": 5878162144,
      "id": "shiba-inu",
      "name": "Shiba Inu",
      "source": "coingecko"
    },
    "UNI": {
      "usd": 8.87,
      "change_24h": 31.60618219481987,
      "change_7d": 68.73107687328032,
      "market_cap": 5597273650,
      "id": "uniswap",
      "name": "Uniswap",
      "source": "coingecko"
    },
    "DOT": {
      "usd": 3.21,
      "change_24h": -0.5607345940712604,
      "change_7d": 21.45906531009729,
      "market_cap": 5248946667,
      "id": "polkadot",
      "name": "Polkadot",
      "source": "coingecko"
    },
    "DAI": {
      "usd": 0.999205,
      "change_24h": -0.02425813877829274,
      "change_7d": 0.04685893935776499,
      "market_cap": 4582613698,
      "id": "dai",
      "name": "Dai",
      "source": "coingecko"
    },
    "NEAR": {
      "usd": 2.74,
      "change_24h": -10.93974846188814,
      "change_7d": 41.55693628744084,
      "market_cap": 3511670439,
      "id": "near",
      "name": "NEAR Protocol",
      "source": "coingecko"
    },
    "ICP": {
      "usd": 6.47,
      "change_24h": -8.688007233609873,
      "change_7d": 28.069944966534642,
      "market_cap": 3501908087,
      "id": "internet-computer",
      "name": "Internet Computer",
      "source": "coingecko"
    },
    "OKB": {
      "usd": 126.21,
      "change_24h": -1.2262396520443255,
      "change_7d": -5.246010363669596,
      "market_cap": 2654832575,
      "id": "okb",
      "name": "OKB",
      "source": "coingecko"
    },
    "ETC": {
      "usd": 16.08,
      "change_24h": -1.3972962956443256,
      "change_7d": 5.333541203233144,
      "market_cap": 2483289128,
      "id": "ethereum-classic",
      "name": "Ethereum Classic",
      "source": "coingecko"
    },
    "APT": {
      "usd": 3.23,
      "change_24h": 0.04784984308098623,
      "change_7d": 15.879789815065692,
      "market_cap": 2328492822,
      "id": "aptos",
      "name": "Aptos",
      "source": "coingecko"
    },
    "POL": {
      "usd": 0.179355,
      "change_24h": -0.9377574578029756,
      "change_7d": 4.126833744888345,
      "market_cap": 1890582175,
      "id": "polygon-ecosystem-token",
      "name": "POL (ex-MATIC)",
      "source": "coingecko"
    },
    "WLD": {
      "usd": 0.813765,
      "change_24h": -1.6816669149239016,
      "change_7d": 11.471344266199127,
      "market_cap": 1849067825,
      "id": "worldcoin-wld",
      "name": "Worldcoin",
      "source": "coingecko"
    },
    "TRUMP": {
      "usd": 8.5,
      "change_24h": 5.343043197922687,
      "change_7d": 18.675634118598992,
      "market_cap": 1699130032,
      "id": "official-trump",
      "name": "Official Trump",
      "source": "coingecko"
    },
    "FIL": {
      "usd": 2.38,
      "change_24h": -11.778481615415071,
      "change_7d": 53.734551445540866,
      "market_cap": 1691666460,
      "id": "filecoin",
      "name": "Filecoin",
      "source": "coingecko"
    },
    "ARB": {
      "usd": 0.299535,
      "change_24h": -0.527101891683178,
      "change_7d": 10.9291920803197,
      "market_cap": 1651052840,
      "id": "arbitrum",
      "name": "Arbitrum",
      "source": "coingecko"
    },
    "ALGO": {
      "usd": 0.182751,
      "change_24h": 1.148305985873542,
      "change_7d": 13.82511210908636,
      "market_cap": 1609458432,
      "id": "algorand",
      "name": "Algorand",
      "source": "coingecko"
    },
    "VET": {
      "usd": 0.0171686,
      "change_24h": -1.0158460511533585,
      "change_7d": 16.045369919246824,
      "market_cap": 1478107350,
      "id": "vechain",
      "name": "VeChain",
      "source": "coingecko"
    },
    "KAS": {
      "usd": 0.052376,
      "change_24h": 0.7047786456530432,
      "change_7d": 13.060081636851246,
      "market_cap": 1402386086,
      "id": "kaspa",
      "name": "Kaspa",
      "source": "coingecko"
    },
    "RENDER": {
      "usd": 2.47,
      "change_24h": 1.2798696897467028,
      "change_7d": 21.647673429138887,
      "market_cap": 1279308439,
      "id": "render-token",
      "name": "Render",
      "source": "coingecko"
    },
    "SEI": {
      "usd": 0.18556,
      "change_24h": 1.3200548568038968,
      "change_7d": 10.689198962289966,
      "market_cap": 1159546872,
      "id": "sei-network",
      "name": "Sei",
      "source": "coingecko"
    },
    "BONK": {
      "usd": 0.00001312,
      "change_24h": -0.9089430082067448,
      "change_7d": 6.88074731386406,
      "market_cap": 1078390474,
      "id": "bonk",
      "name": "Bonk",
      "source": "coingecko"
    },
    "PENGU": {
      "usd": 0.01583834,
      "change_24h": -0.9457048600503726,
      "change_7d": 1.9214375413999878,
      "market_cap": 995772758,
      "id": "pudgy-penguins",
      "name": "Pudgy Penguins",
      "source": "coingecko"
    },
    "IMX": {
      "usd": 0.473329,
      "change_24h": 6.160301426504344,
      "change_7d": 5.965636232513672,
      "market_cap": 930132767,
      "id": "immutable-x",
      "name": "Immutable",
      "source": "coingecko"
    },
    "OP": {
      "usd": 0.432827,
      "change_24h": -0.612294829145691,
      "change_7d": 18.836295565665917,
      "market_cap": 820676663,
      "id": "optimism",
      "name": "Optimism",
      "source": "coingecko"
    },
    "GRT": {
      "usd": 0.067016,
      "change_24h": -2.205792330652297,
      "change_7d": 17.173830837353833,
      "market_cap": 708509035,
      "id": "the-graph",
      "name": "The Graph",
      "source": "coingecko"
    },
    "CFX": {
      "usd": 0.099278,
      "change_24h": -0.8552125694557744,
      "change_7d": 8.98437962602056,
      "market_cap": 512189300,
      "id": "conflux-token",
      "name": "Conflux",
      "source": "coingecko"
    },
    "GALA": {
      "usd": 0.01040043,
      "change_24h": 0.969460284669666,
      "change_7d": 14.426231014506183,
      "market_cap": 484414194,
      "id": "gala",
      "name": "GALA",
      "source": "coingecko"
    },
    "FLOW": {
      "usd": 0.281492,
      "change_24h": -0.26503264484405764,
      "change_7d": 14.594221082282452,
      "market_cap": 456363145,
      "id": "flow",
      "name": "Flow",
      "source": "coingecko"
    },
    "FRAX": {
      "usd": 0.994201,
      "change_24h": -0.05357600660372321,
      "change_7d": -0.11493928092947729,
      "market_cap": 289101244,
      "id": "frax",
      "name": "Legacy Frax Dollar",
      "source": "coingecko"
    },
    "RUNE": {
      "usd": 0.806889,
      "change_24h": -3.6949183937282277,
      "change_7d": 1.9466374993052034,
      "market_cap": 283805281,
      "id": "thorchain",
      "name": "THORChain",
      "source": "coingecko"
    },
    "MINA": {
      "usd": 0.150254,
      "change_24h": -3.7434149513270136,
      "change_7d": 10.783777920659867,
      "market_cap": 189963450,
      "id": "mina-protocol",
      "name": "Mina Protocol",
      "source": "coingecko"
    },
    "BOME": {
      "usd": 0.00095273,
      "change_24h": -1.7427934600356896,
      "change_7d": 11.061600704131008,
      "market_cap": 65701013,
      "id": "book-of-meme",
      "name": "BOOK OF MEME",
      "source": "coingecko"
    },
    "GOAT": {
      "usd": 0.04979742,
      "change_24h": -3.320977939404661,
      "change_7d": 7.220075180959473,
      "market_cap": 49739331,
      "id": "goatseus-maximus",
      "name": "Goatseus Maximus",
      "source": "coingecko"
    },
    "STREAM": {
      "usd": 0.02326646,
      "change_24h": -3.09838233767103,
      "change_7d": -9.427523771483196,
      "market_cap": 3169768,
      "id": "streamflow",
      "name": "Streamflow",
      "source": "coingecko"
    },
    "CHILLGUY": {
      "usd": 0.00016388,
      "change_24h": -0.8157643391399202,
      "change_7d": -2.750505025533564,
      "market_cap": 163884,
      "id": "just-a-chill-guy",
      "name": "Just a chill guy (ETH)",
      "source": "coingecko"
    },
    "FTM": {
      "usd": 0.154399,
      "change_24h": -3.22837678211112,
      "change_7d": 10.662724514385804,
      "market_cap": 0,
      "id": "fantom",
      "name": "Fantom",
      "source": "coingecko"
    },
    "MKR": {
      "usd": 1339.56,
      "change_24h": 3.1683609115281723,
      "change_7d": 4.515119789516912,
      "market_cap": 0,
      "id": "maker",
      "name": "Maker",
      "source": "coingecko"
    }
  }
}