{
  "updated_at": "2025-09-03T15:33:45.751Z",
  "meta": {
    "included_ids": [
      "bitcoin",
      "ethereum",
      "tether",
      "binancecoin",
      "solana",
      "ripple",
      "usd-coin",
      "staked-ether",
      "cardano",
      "dogecoin",
      "avalanche-2",
      "tron",
      "shiba-inu",
      "wrapped-bitcoin",
      "polkadot",
      "chainlink",
      "bitcoin-cash",
      "uniswap",
      "litecoin",
      "internet-computer",
      "dai",
      "near",
      "ethereum-classic",
      "filecoin",
      "aptos",
      "leo-token",
      "stellar",
      "okb",
      "vechain",
      "render-token",
      "monero",
      "arbitrum",
      "fantom",
      "the-graph",
      "immutable-x",
      "maker",
      "kaspa",
      "gala",
      "optimism",
      "frax",
      "sei-network",
      "algorand",
      "flow",
      "thorchain",
      "conflux-token",
      "mina-protocol",
      "worldcoin-wld",
      "polygon-ecosystem-token",
      "bonk",
      "book-of-meme",
      "official-trump",
      "streamflow",
      "pudgy-penguins",
      "just-a-chill-guy",
      "goatseus-maximus"
    ],
    "wallet_resolved": [
      {
        "raw": "worldcoin",
        "resolved": "worldcoin-wld",
        "via": "override"
      },
      {
        "raw": "pol",
        "resolved": "polygon-ecosystem-token",
        "via": "override"
      },
      {
        "raw": "bonk",
        "resolved": "bonk",
        "via": "id"
      },
      {
        "raw": "bome",
        "resolved": "book-of-meme",
        "via": "override"
      },
      {
        "raw": "official-trump",
        "resolved": "official-trump",
        "via": "id"
      },
      {
        "raw": "streamflow",
        "resolved": "streamflow",
        "via": "id"
      },
      {
        "raw": "pengu",
        "resolved": "pudgy-penguins",
        "via": "override"
      },
      {
        "raw": "just-a-chill-guy",
        "resolved": "just-a-chill-guy",
        "via": "id"
      },
      {
        "raw": "goatseus-maximus",
        "resolved": "goatseus-maximus",
        "via": "id"
      },
      {
        "raw": "optimism",
        "resolved": "optimism",
        "via": "id"
      },
      {
        "raw": "solana",
        "resolved": "solana",
        "via": "id"
      },
      {
        "raw": "ripple",
        "resolved": "ripple",
        "via": "id"
      }
    ],
    "missing": [],
    "ambiguous": []
  },
  "assets": {
    "BTC": {
      "usd": 112018,
      "change_24h": 0.9181127274071653,
      "change_7d": 0.1188702721215461,
      "market_cap": 2230281917839,
      "id": "bitcoin",
      "name": "Bitcoin",
      "source": "coingecko"
    },
    "ETH": {
      "usd": 4461.05,
      "change_24h": 3.3800053248469673,
      "change_7d": -3.013172605970537,
      "market_cap": 538160347777,
      "id": "ethereum",
      "name": "Ethereum",
      "source": "coingecko"
    },
    "XRP": {
      "usd": 2.86,
      "change_24h": 1.3807302862079551,
      "change_7d": -4.603595944436283,
      "market_cap": 170403132662,
      "id": "ripple",
      "name": "XRP",
      "source": "coingecko"
    },
    "USDT": {
      "usd": 1,
      "change_24h": 0.0163194672886885,
      "change_7d": 0.0030224201134941295,
      "market_cap": 168175045084,
      "id": "tether",
      "name": "Tether",
      "source": "coingecko"
    },
    "BNB": {
      "usd": 858.95,
      "change_24h": 1.1124470136523419,
      "change_7d": -0.09715328789629128,
      "market_cap": 119554513400,
      "id": "binancecoin",
      "name": "BNB",
      "source": "coingecko"
    },
    "SOL": {
      "usd": 211.61,
      "change_24h": 4.212453545153269,
      "change_7d": 3.3964356189138263,
      "market_cap": 114457494971,
      "id": "solana",
      "name": "Solana",
      "source": "coingecko"
    },
    "USDC": {
      "usd": 0.999809,
      "change_24h": -0.000430331489124674,
      "change_7d": 0.0026167279460496116,
      "market_cap": 72008260974,
      "id": "usd-coin",
      "name": "USDC",
      "source": "coingecko"
    },
    "STETH": {
      "usd": 4449.27,
      "change_24h": 3.154223626204323,
      "change_7d": -3.190811641861613,
      "market_cap": 38593063421,
      "id": "staked-ether",
      "name": "Lido Staked Ether",
      "source": "coingecko"
    },
    "DOGE": {
      "usd": 0.218391,
      "change_24h": 3.350843725526421,
      "change_7d": -0.5032273874193743,
      "market_cap": 32918080210,
      "id": "dogecoin",
      "name": "Dogecoin",
      "source": "coingecko"
    },
    "TRX": {
      "usd": 0.340758,
      "change_24h": 0.7985232567776459,
      "change_7d": -2.5923864445952334,
      "market_cap": 32256948219,
      "id": "tron",
      "name": "TRON",
      "source": "coingecko"
    },
    "ADA": {
      "usd": 0.83688,
      "change_24h": 2.314452492785532,
      "change_7d": -3.737977220914499,
      "market_cap": 30530154221,
      "id": "cardano",
      "name": "Cardano",
      "source": "coingecko"
    },
    "LINK": {
      "usd": 23.65,
      "change_24h": 2.155811966512211,
      "change_7d": -2.8165001711519317,
      "market_cap": 16037577146,
      "id": "chainlink",
      "name": "Chainlink",
      "source": "coingecko"
    },
    "WBTC": {
      "usd": 112039,
      "change_24h": 1.0655030959758478,
      "change_7d": 0.11643744595038343,
      "market_cap": 14235791558,
      "id": "wrapped-bitcoin",
      "name": "Wrapped Bitcoin",
      "source": "coingecko"
    },
    "BCH": {
      "usd": 598.55,
      "change_24h": 3.9797507148958076,
      "change_7d": 7.147530894786369,
      "market_cap": 11923053147,
      "id": "bitcoin-cash",
      "name": "Bitcoin Cash",
      "source": "coingecko"
    },
    "XLM": {
      "usd": 0.366534,
      "change_24h": 1.0540796460062711,
      "change_7d": -4.869934029339818,
      "market_cap": 11631007851,
      "id": "stellar",
      "name": "Stellar",
      "source": "coingecko"
    },
    "AVAX": {
      "usd": 25.39,
      "change_24h": 6.801947019399841,
      "change_7d": 2.5373676382346555,
      "market_cap": 10736209261,
      "id": "avalanche-2",
      "name": "Avalanche",
      "source": "coingecko"
    },
    "LEO": {
      "usd": 9.5,
      "change_24h": -0.6094033546671902,
      "change_7d": -0.10150776322488435,
      "market_cap": 8772926867,
      "id": "leo-token",
      "name": "LEO Token",
      "source": "coingecko"
    },
    "LTC": {
      "usd": 112.79,
      "change_24h": 1.8842211818383419,
      "change_7d": -0.5966830130470506,
      "market_cap": 8601214971,
      "id": "litecoin",
      "name": "Litecoin",
      "source": "coingecko"
    },
    "SHIB": {
      "usd": 0.00001249,
      "change_24h": 1.3088106279725413,
      "change_7d": -0.34060365787836233,
      "market_cap": 7360979731,
      "id": "shiba-inu",
      "name": "Shiba Inu",
      "source": "coingecko"
    },
    "DOT": {
      "usd": 3.88,
      "change_24h": 3.08557112846679,
      "change_7d": -0.06013671556533978,
      "market_cap": 5897501905,
      "id": "polkadot",
      "name": "Polkadot",
      "source": "coingecko"
    },
    "UNI": {
      "usd": 9.66,
      "change_24h": 2.205352381596141,
      "change_7d": -2.96651663954912,
      "market_cap": 5802847005,
      "id": "uniswap",
      "name": "Uniswap",
      "source": "coingecko"
    },
    "XMR": {
      "usd": 268.9,
      "change_24h": 2.792018738280786,
      "change_7d": 0.4307800408754008,
      "market_cap": 4963452741,
      "id": "monero",
      "name": "Monero",
      "source": "coingecko"
    },
    "DAI": {
      "usd": 1,
      "change_24h": -0.04063226385749529,
      "change_7d": 0.019984710801361175,
      "market_cap": 4607920694,
      "id": "dai",
      "name": "Dai",
      "source": "coingecko"
    },
    "OKB": {
      "usd": 180.22,
      "change_24h": 8.984851451994233,
      "change_7d": 3.319373720179165,
      "market_cap": 3782480633,
      "id": "okb",
      "name": "OKB",
      "source": "coingecko"
    },
    "ETC": {
      "usd": 21.01,
      "change_24h": 1.5713866307087239,
      "change_7d": -3.121966520687627,
      "market_cap": 3221444486,
      "id": "ethereum-classic",
      "name": "Ethereum Classic",
      "source": "coingecko"
    },
    "NEAR": {
      "usd": 2.47,
      "change_24h": 4.090365755517194,
      "change_7d": -2.6834031501253186,
      "market_cap": 3089648527,
      "id": "near",
      "name": "NEAR Protocol",
      "source": "coingecko"
    },
    "APT": {
      "usd": 4.36,
      "change_24h": 1.4320303055146875,
      "change_7d": -0.40575506427833413,
      "market_cap": 2996504760,
      "id": "aptos",
      "name": "Aptos",
      "source": "coingecko"
    },
    "POL": {
      "usd": 0.285169,
      "change_24h": -0.40106056698869397,
      "change_7d": 17.050460981521194,
      "market_cap": 2995123646,
      "id": "polygon-ecosystem-token",
      "name": "POL (ex-MATIC)",
      "source": "coingecko"
    },
    "ARB": {
      "usd": 0.512693,
      "change_24h": 4.902834305363863,
      "change_7d": -1.6214413490570603,
      "market_cap": 2715588828,
      "id": "arbitrum",
      "name": "Arbitrum",
      "source": "coingecko"
    },
    "ICP": {
      "usd": 4.88,
      "change_24h": 1.6439577326672266,
      "change_7d": -3.272369405560012,
      "market_cap": 2621648186,
      "id": "internet-computer",
      "name": "Internet Computer",
      "source": "coingecko"
    },
    "KAS": {
      "usd": 0.084884,
      "change_24h": 1.0309086819988735,
      "change_7d": -3.7088784203008913,
      "market_cap": 2238832621,
      "id": "kaspa",
      "name": "Kaspa",
      "source": "coingecko"
    },
    "VET": {
      "usd": 0.02398846,
      "change_24h": 1.2561584664958185,
      "change_7d": -4.0776102558494305,
      "market_cap": 2062233854,
      "id": "vechain",
      "name": "VeChain",
      "source": "coingecko"
    },
    "ALGO": {
      "usd": 0.235567,
      "change_24h": 2.4111033286195256,
      "change_7d": -6.678452480162636,
      "market_cap": 2057638389,
      "id": "algorand",
      "name": "Algorand",
      "source": "coingecko"
    },
    "PENGU": {
      "usd": 0.03076639,
      "change_24h": 4.527545110635375,
      "change_7d": -0.5954720331340588,
      "market_cap": 1933061404,
      "id": "pudgy-penguins",
      "name": "Pudgy Penguins",
      "source": "coingecko"
    },
    "RENDER": {
      "usd": 3.5,
      "change_24h": 2.502601723967778,
      "change_7d": -2.873156229140452,
      "market_cap": 1814095562,
      "id": "render-token",
      "name": "Render",
      "source": "coingecko"
    },
    "WLD": {
      "usd": 0.896607,
      "change_24h": 2.782271729827901,
      "change_7d": -4.824935918500491,
      "market_cap": 1791802188,
      "id": "worldcoin-wld",
      "name": "Worldcoin",
      "source": "coingecko"
    },
    "SEI": {
      "usd": 0.292091,
      "change_24h": 3.182553199176729,
      "change_7d": -3.0049909015541445,
      "market_cap": 1755645661,
      "id": "sei-network",
      "name": "Sei",
      "source": "coingecko"
    },
    "TRUMP": {
      "usd": 8.43,
      "change_24h": 0.6540756160770669,
      "change_7d": -0.4681837137370721,
      "market_cap": 1684803610,
      "id": "official-trump",
      "name": "Official Trump",
      "source": "coingecko"
    },
    "BONK": {
      "usd": 0.00002058,
      "change_24h": 2.0084868582924957,
      "change_7d": -3.5168620417978422,
      "market_cap": 1593769721,
      "id": "bonk",
      "name": "Bonk",
      "source": "coingecko"
    },
    "FIL": {
      "usd": 2.32,
      "change_24h": 2.5608732264161533,
      "change_7d": -0.13505533529855218,
      "market_cap": 1587281904,
      "id": "filecoin",
      "name": "Filecoin",
      "source": "coingecko"
    },
    "OP": {
      "usd": 0.721019,
      "change_24h": 2.9720747696142977,
      "change_7d": 2.8186707851439703,
      "market_cap": 1281870971,
      "id": "optimism",
      "name": "Optimism",
      "source": "coingecko"
    },
    "IMX": {
      "usd": 0.524315,
      "change_24h": 2.1676303497913727,
      "change_7d": -4.033973833767967,
      "market_cap": 1004273337,
      "id": "immutable-x",
      "name": "Immutable",
      "source": "coingecko"
    },
    "GRT": {
      "usd": 0.09026,
      "change_24h": 2.748167737943461,
      "change_7d": 0.331460539775946,
      "market_cap": 945103401,
      "id": "the-graph",
      "name": "The Graph",
      "source": "coingecko"
    },
    "CFX": {
      "usd": 0.177276,
      "change_24h": 2.0766450997918033,
      "change_7d": 2.6717624512381692,
      "market_cap": 909445910,
      "id": "conflux-token",
      "name": "Conflux",
      "source": "coingecko"
    },
    "GALA": {
      "usd": 0.01625985,
      "change_24h": 2.2619763125777035,
      "change_7d": -2.2508248078331228,
      "market_cap": 745655296,
      "id": "gala",
      "name": "GALA",
      "source": "coingecko"
    },
    "FLOW": {
      "usd": 0.413493,
      "change_24h": 3.0952107818094015,
      "change_7d": 6.243137944563369,
      "market_cap": 663806127,
      "id": "flow",
      "name": "Flow",
      "source": "coingecko"
    },
    "RUNE": {
      "usd": 1.21,
      "change_24h": 2.350277940512135,
      "change_7d": -3.055975108032115,
      "market_cap": 427034331,
      "id": "thorchain",
      "name": "THORChain",
      "source": "coingecko"
    },
    "FRAX": {
      "usd": 0.998342,
      "change_24h": 0.04365439131639437,
      "change_7d": 0.02902390813340715,
      "market_cap": 296409484,
      "id": "frax",
      "name": "Legacy Frax Dollar",
      "source": "coingecko"
    },
    "MINA": {
      "usd": 0.180703,
      "change_24h": 1.842144954394989,
      "change_7d": -0.07673543470227152,
      "market_cap": 225931193,
      "id": "mina-protocol",
      "name": "Mina Protocol",
      "source": "coingecko"
    },
    "BOME": {
      "usd": 0.00194356,
      "change_24h": 3.4613036068652563,
      "change_7d": -2.6174401121857143,
      "market_cap": 134083376,
      "id": "book-of-meme",
      "name": "BOOK OF MEME",
      "source": "coingecko"
    },
    "GOAT": {
      "usd": 0.083212,
      "change_24h": 4.177281924275976,
      "change_7d": -2.689431729529671,
      "market_cap": 83104211,
      "id": "goatseus-maximus",
      "name": "Goatseus Maximus",
      "source": "coingecko"
    },
    "STREAM": {
      "usd": 0.051901,
      "change_24h": 0.7599013568953643,
      "change_7d": 5.945205006810542,
      "market_cap": 7042607,
      "id": "streamflow",
      "name": "Streamflow",
      "source": "coingecko"
    },
    "CHILLGUY": {
      "usd": 0.00031256,
      "change_24h": 2.203468728207255,
      "change_7d": -7.674272608570017,
      "market_cap": 312563,
      "id": "just-a-chill-guy",
      "name": "Just a chill guy (ETH)",
      "source": "coingecko"
    },
    "FTM": {
      "usd": 0.308206,
      "change_24h": 0.2625596725921883,
      "change_7d": -2.9197453154154727,
      "market_cap": 0,
      "id": "fantom",
      "name": "Fantom",
      "source": "coingecko"
    },
    "MKR": {
      "usd": 1742.23,
      "change_24h": -2.187515648523851,
      "change_7d": 10.075061952847244,
      "market_cap": 0,
      "id": "maker",
      "name": "Maker",
      "source": "coingecko"
    }
  }
}