{
  "updated_at": "2025-11-15T07:28:50.618Z",
  "meta": {
    "included_ids": [
      "bitcoin",
      "ethereum",
      "tether",
      "binancecoin",
      "solana",
      "ripple",
      "usd-coin",
      "staked-ether",
      "cardano",
      "dogecoin",
      "avalanche-2",
      "tron",
      "shiba-inu",
      "wrapped-bitcoin",
      "polkadot",
      "chainlink",
      "bitcoin-cash",
      "uniswap",
      "litecoin",
      "internet-computer",
      "dai",
      "near",
      "ethereum-classic",
      "filecoin",
      "aptos",
      "leo-token",
      "stellar",
      "okb",
      "vechain",
      "render-token",
      "monero",
      "arbitrum",
      "fantom",
      "the-graph",
      "immutable-x",
      "maker",
      "kaspa",
      "gala",
      "optimism",
      "frax",
      "sei-network",
      "algorand",
      "flow",
      "thorchain",
      "conflux-token",
      "mina-protocol",
      "worldcoin-wld",
      "polygon-ecosystem-token",
      "bonk",
      "book-of-meme",
      "official-trump",
      "streamflow",
      "pudgy-penguins",
      "just-a-chill-guy",
      "goatseus-maximus"
    ],
    "wallet_resolved": [
      {
        "raw": "worldcoin",
        "resolved": "worldcoin-wld",
        "via": "override"
      },
      {
        "raw": "pol",
        "resolved": "polygon-ecosystem-token",
        "via": "override"
      },
      {
        "raw": "bonk",
        "resolved": "bonk",
        "via": "id"
      },
      {
        "raw": "bome",
        "resolved": "book-of-meme",
        "via": "override"
      },
      {
        "raw": "official-trump",
        "resolved": "official-trump",
        "via": "id"
      },
      {
        "raw": "streamflow",
        "resolved": "streamflow",
        "via": "id"
      },
      {
        "raw": "pengu",
        "resolved": "pudgy-penguins",
        "via": "override"
      },
      {
        "raw": "just-a-chill-guy",
        "resolved": "just-a-chill-guy",
        "via": "id"
      },
      {
        "raw": "goatseus-maximus",
        "resolved": "goatseus-maximus",
        "via": "id"
      },
      {
        "raw": "optimism",
        "resolved": "optimism",
        "via": "id"
      },
      {
        "raw": "solana",
        "resolved": "solana",
        "via": "id"
      },
      {
        "raw": "ripple",
        "resolved": "ripple",
        "via": "id"
      }
    ],
    "missing": [],
    "ambiguous": []
  },
  "assets": {
    "BTC": {
      "usd": 96278,
      "change_24h": -1.3293519011085122,
      "change_7d": -5.79732321174068,
      "market_cap": 1915190041971,
      "id": "bitcoin",
      "name": "Bitcoin",
      "source": "coingecko"
    },
    "ETH": {
      "usd": 3181.13,
      "change_24h": -0.943022586797055,
      "change_7d": -7.254489572105903,
      "market_cap": 383441394678,
      "id": "ethereum",
      "name": "Ethereum",
      "source": "coingecko"
    },
    "USDT": {
      "usd": 0.999538,
      "change_24h": -0.01778019385286296,
      "change_7d": 0.009814696268577696,
      "market_cap": 183947590274,
      "id": "tether",
      "name": "Tether",
      "source": "coingecko"
    },
    "XRP": {
      "usd": 2.28,
      "change_24h": -1.2235520611288273,
      "change_7d": -1.4775532648060714,
      "market_cap": 137384046902,
      "id": "ripple",
      "name": "XRP",
      "source": "coingecko"
    },
    "BNB": {
      "usd": 935.9,
      "change_24h": 1.5059754962079788,
      "change_7d": -5.811310326143171,
      "market_cap": 128587460769,
      "id": "binancecoin",
      "name": "BNB",
      "source": "coingecko"
    },
    "SOL": {
      "usd": 143,
      "change_24h": -0.43178759909420306,
      "change_7d": -11.365999433906332,
      "market_cap": 79247814495,
      "id": "solana",
      "name": "Solana",
      "source": "coingecko"
    },
    "USDC": {
      "usd": 0.999748,
      "change_24h": -0.0050277979169710005,
      "change_7d": -0.005167506673042678,
      "market_cap": 74914477828,
      "id": "usd-coin",
      "name": "USDC",
      "source": "coingecko"
    },
    "TRX": {
      "usd": 0.294092,
      "change_24h": 0.6072207023918239,
      "change_7d": 0.9127924411118155,
      "market_cap": 27816596461,
      "id": "tron",
      "name": "TRON",
      "source": "coingecko"
    },
    "STETH": {
      "usd": 3180.03,
      "change_24h": -1.0155337885130735,
      "change_7d": -7.229211831585869,
      "market_cap": 27456628805,
      "id": "staked-ether",
      "name": "Lido Staked Ether",
      "source": "coingecko"
    },
    "DOGE": {
      "usd": 0.163323,
      "change_24h": -1.1286833114914716,
      "change_7d": -8.65252637735207,
      "market_cap": 24753771548,
      "id": "dogecoin",
      "name": "Dogecoin",
      "source": "coingecko"
    },
    "ADA": {
      "usd": 0.513164,
      "change_24h": -2.0739576601034666,
      "change_7d": -11.417217978572456,
      "market_cap": 18765143204,
      "id": "cardano",
      "name": "Cardano",
      "source": "coingecko"
    },
    "WBTC": {
      "usd": 96074,
      "change_24h": -1.0735716275457068,
      "change_7d": -5.84069461651111,
      "market_cap": 12175601481,
      "id": "wrapped-bitcoin",
      "name": "Wrapped Bitcoin",
      "source": "coingecko"
    },
    "BCH": {
      "usd": 495.14,
      "change_24h": -1.2392210701031443,
      "change_7d": -0.8601785825841967,
      "market_cap": 9873103942,
      "id": "bitcoin-cash",
      "name": "Bitcoin Cash",
      "source": "coingecko"
    },
    "LINK": {
      "usd": 14.15,
      "change_24h": -2.1518129245899376,
      "change_7d": -9.90879372482743,
      "market_cap": 9856772448,
      "id": "chainlink",
      "name": "Chainlink",
      "source": "coingecko"
    },
    "XLM": {
      "usd": 0.264897,
      "change_24h": -1.7622851973715774,
      "change_7d": -7.980950751805284,
      "market_cap": 8504280825,
      "id": "stellar",
      "name": "Stellar",
      "source": "coingecko"
    },
    "LEO": {
      "usd": 9.21,
      "change_24h": 0.20388221013263289,
      "change_7d": 0.43058193187261806,
      "market_cap": 8494711523,
      "id": "leo-token",
      "name": "LEO Token",
      "source": "coingecko"
    },
    "LTC": {
      "usd": 103.83,
      "change_24h": 5.803392086078334,
      "change_7d": 3.641724984411475,
      "market_cap": 7923411939,
      "id": "litecoin",
      "name": "Litecoin",
      "source": "coingecko"
    },
    "XMR": {
      "usd": 414.11,
      "change_24h": 5.8396255303891405,
      "change_7d": 14.85206078910524,
      "market_cap": 7620700146,
      "id": "monero",
      "name": "Monero",
      "source": "coingecko"
    },
    "AVAX": {
      "usd": 15.64,
      "change_24h": -2.114707441657402,
      "change_7d": -11.753066242007524,
      "market_cap": 6705121910,
      "id": "avalanche-2",
      "name": "Avalanche",
      "source": "coingecko"
    },
    "SHIB": {
      "usd": 0.00000922,
      "change_24h": -0.2998530607193504,
      "change_7d": -7.505851549042257,
      "market_cap": 5432526975,
      "id": "shiba-inu",
      "name": "Shiba Inu",
      "source": "coingecko"
    },
    "DOT": {
      "usd": 2.92,
      "change_24h": 0.5902761100064243,
      "change_7d": -12.89078654281913,
      "market_cap": 4777637802,
      "id": "polkadot",
      "name": "Polkadot",
      "source": "coingecko"
    },
    "UNI": {
      "usd": 7.5,
      "change_24h": -0.755657680875802,
      "change_7d": 25.709452634807988,
      "market_cap": 4724295073,
      "id": "uniswap",
      "name": "Uniswap",
      "source": "coingecko"
    },
    "DAI": {
      "usd": 0.999976,
      "change_24h": 0.13614815342437264,
      "change_7d": -0.0003929767419999216,
      "market_cap": 4527091804,
      "id": "dai",
      "name": "Dai",
      "source": "coingecko"
    },
    "NEAR": {
      "usd": 2.54,
      "change_24h": 4.982048751423957,
      "change_7d": -4.438060616227599,
      "market_cap": 3254359144,
      "id": "near",
      "name": "NEAR Protocol",
      "source": "coingecko"
    },
    "ICP": {
      "usd": 5.48,
      "change_24h": -9.062974770579153,
      "change_7d": -42.81236308753502,
      "market_cap": 2957384145,
      "id": "internet-computer",
      "name": "Internet Computer",
      "source": "coingecko"
    },
    "ETC": {
      "usd": 15.51,
      "change_24h": 2.9214907083840025,
      "change_7d": -7.570233594177357,
      "market_cap": 2400486954,
      "id": "ethereum-classic",
      "name": "Ethereum Classic",
      "source": "coingecko"
    },
    "OKB": {
      "usd": 112.56,
      "change_24h": -2.0336390437532854,
      "change_7d": -9.265518013344295,
      "market_cap": 2358071544,
      "id": "okb",
      "name": "OKB",
      "source": "coingecko"
    },
    "APT": {
      "usd": 2.97,
      "change_24h": 0.9308949747543982,
      "change_7d": -3.82993154899487,
      "market_cap": 2184314617,
      "id": "aptos",
      "name": "Aptos",
      "source": "coingecko"
    },
    "WLD": {
      "usd": 0.716309,
      "change_24h": -3.4552683983175814,
      "change_7d": -12.635229933760467,
      "market_cap": 1663800551,
      "id": "worldcoin-wld",
      "name": "Worldcoin",
      "source": "coingecko"
    },
    "POL": {
      "usd": 0.156063,
      "change_24h": -5.783187777329162,
      "change_7d": -13.165572180238637,
      "market_cap": 1644958866,
      "id": "polygon-ecosystem-token",
      "name": "POL (ex-MATIC)",
      "source": "coingecko"
    },
    "FIL": {
      "usd": 2.11,
      "change_24h": -0.20709940817896624,
      "change_7d": -32.16411097826875,
      "market_cap": 1505818017,
      "id": "filecoin",
      "name": "Filecoin",
      "source": "coingecko"
    },
    "ALGO": {
      "usd": 0.166298,
      "change_24h": 0.38706229512372314,
      "change_7d": -6.3547751915683195,
      "market_cap": 1460573519,
      "id": "algorand",
      "name": "Algorand",
      "source": "coingecko"
    },
    "TRUMP": {
      "usd": 7.26,
      "change_24h": 0.8127976442573869,
      "change_7d": -6.132549760675129,
      "market_cap": 1451843140,
      "id": "official-trump",
      "name": "Official Trump",
      "source": "coingecko"
    },
    "VET": {
      "usd": 0.0160392,
      "change_24h": 0.2883345934513362,
      "change_7d": -5.076533633878108,
      "market_cap": 1379789920,
      "id": "vechain",
      "name": "VeChain",
      "source": "coingecko"
    },
    "ARB": {
      "usd": 0.246939,
      "change_24h": 0.8592376428942847,
      "change_7d": -17.45553691794761,
      "market_cap": 1360539117,
      "id": "arbitrum",
      "name": "Arbitrum",
      "source": "coingecko"
    },
    "KAS": {
      "usd": 0.04573422,
      "change_24h": -3.0938161983678016,
      "change_7d": -8.160964180334034,
      "market_cap": 1223486493,
      "id": "kaspa",
      "name": "Kaspa",
      "source": "coingecko"
    },
    "RENDER": {
      "usd": 2.2,
      "change_24h": -1.6037964840145218,
      "change_7d": -6.057554057503516,
      "market_cap": 1142450447,
      "id": "render-token",
      "name": "Render",
      "source": "coingecko"
    },
    "SEI": {
      "usd": 0.164081,
      "change_24h": -1.3738245816318133,
      "change_7d": -9.868609176057424,
      "market_cap": 1044469507,
      "id": "sei-network",
      "name": "Sei",
      "source": "coingecko"
    },
    "BONK": {
      "usd": 0.0000114,
      "change_24h": -0.8799447205594174,
      "change_7d": -12.484288473762021,
      "market_cap": 936736374,
      "id": "bonk",
      "name": "Bonk",
      "source": "coingecko"
    },
    "PENGU": {
      "usd": 0.01337685,
      "change_24h": -0.1357116425339007,
      "change_7d": -12.582764934982022,
      "market_cap": 840848323,
      "id": "pudgy-penguins",
      "name": "Pudgy Penguins",
      "source": "coingecko"
    },
    "IMX": {
      "usd": 0.390007,
      "change_24h": -1.0020765338209174,
      "change_7d": -10.291454244551536,
      "market_cap": 766161508,
      "id": "immutable-x",
      "name": "Immutable",
      "source": "coingecko"
    },
    "OP": {
      "usd": 0.397055,
      "change_24h": 1.6352148636583468,
      "change_7d": -6.095709630427913,
      "market_cap": 752392070,
      "id": "optimism",
      "name": "Optimism",
      "source": "coingecko"
    },
    "GRT": {
      "usd": 0.058411,
      "change_24h": -2.3584467734657264,
      "change_7d": -12.456893500152642,
      "market_cap": 617904594,
      "id": "the-graph",
      "name": "The Graph",
      "source": "coingecko"
    },
    "CFX": {
      "usd": 0.088837,
      "change_24h": -0.6940116648054719,
      "change_7d": -15.883269666651659,
      "market_cap": 457806129,
      "id": "conflux-token",
      "name": "Conflux",
      "source": "coingecko"
    },
    "GALA": {
      "usd": 0.00932305,
      "change_24h": 0.7446821669351136,
      "change_7d": -7.446359660593899,
      "market_cap": 434269310,
      "id": "gala",
      "name": "GALA",
      "source": "coingecko"
    },
    "FLOW": {
      "usd": 0.264732,
      "change_24h": 1.42272837117933,
      "change_7d": -4.863818626162743,
      "market_cap": 429222059,
      "id": "flow",
      "name": "Flow",
      "source": "coingecko"
    },
    "FRAX": {
      "usd": 0.994189,
      "change_24h": 0.0006718446208253799,
      "change_7d": -0.04113909792206272,
      "market_cap": 284615287,
      "id": "frax",
      "name": "Legacy Frax Dollar",
      "source": "coingecko"
    },
    "RUNE": {
      "usd": 0.739196,
      "change_24h": -1.4536966156448232,
      "change_7d": -8.311968329403348,
      "market_cap": 259211304,
      "id": "thorchain",
      "name": "THORChain",
      "source": "coingecko"
    },
    "MINA": {
      "usd": 0.138327,
      "change_24h": 2.4998113764503316,
      "change_7d": -20.91527342313751,
      "market_cap": 174465557,
      "id": "mina-protocol",
      "name": "Mina Protocol",
      "source": "coingecko"
    },
    "BOME": {
      "usd": 0.00084252,
      "change_24h": 0.7340731695231175,
      "change_7d": -10.966824342723044,
      "market_cap": 58139549,
      "id": "book-of-meme",
      "name": "BOOK OF MEME",
      "source": "coingecko"
    },
    "GOAT": {
      "usd": 0.04265389,
      "change_24h": -0.0373876853612176,
      "change_7d": -12.726805331483849,
      "market_cap": 42517287,
      "id": "goatseus-maximus",
      "name": "Goatseus Maximus",
      "source": "coingecko"
    },
    "STREAM": {
      "usd": 0.02014735,
      "change_24h": -1.861481003148096,
      "change_7d": -15.39956512486996,
      "market_cap": 2746032,
      "id": "streamflow",
      "name": "Streamflow",
      "source": "coingecko"
    },
    "CHILLGUY": {
      "usd": 0.00014276,
      "change_24h": 2.6517396262242454,
      "change_7d": -7.0113592049546964,
      "market_cap": 142780,
      "id": "just-a-chill-guy",
      "name": "Just a chill guy (ETH)",
      "source": "coingecko"
    },
    "FTM": {
      "usd": 0.133251,
      "change_24h": -5.883122642085458,
      "change_7d": -16.277738478292527,
      "market_cap": 0,
      "id": "fantom",
      "name": "Fantom",
      "source": "coingecko"
    },
    "MKR": {
      "usd": 1236.05,
      "change_24h": -7.083193358668932,
      "change_7d": -3.535628354025385,
      "market_cap": 0,
      "id": "maker",
      "name": "Maker",
      "source": "coingecko"
    }
  }
}