{
  "updated_at": "2025-10-04T08:59:12.967Z",
  "meta": {
    "included_ids": [
      "bitcoin",
      "ethereum",
      "tether",
      "binancecoin",
      "solana",
      "ripple",
      "usd-coin",
      "staked-ether",
      "cardano",
      "dogecoin",
      "avalanche-2",
      "tron",
      "shiba-inu",
      "wrapped-bitcoin",
      "polkadot",
      "chainlink",
      "bitcoin-cash",
      "uniswap",
      "litecoin",
      "internet-computer",
      "dai",
      "near",
      "ethereum-classic",
      "filecoin",
      "aptos",
      "leo-token",
      "stellar",
      "okb",
      "vechain",
      "render-token",
      "monero",
      "arbitrum",
      "fantom",
      "the-graph",
      "immutable-x",
      "maker",
      "kaspa",
      "gala",
      "optimism",
      "frax",
      "sei-network",
      "algorand",
      "flow",
      "thorchain",
      "conflux-token",
      "mina-protocol",
      "worldcoin-wld",
      "polygon-ecosystem-token",
      "bonk",
      "book-of-meme",
      "official-trump",
      "streamflow",
      "pudgy-penguins",
      "just-a-chill-guy",
      "goatseus-maximus"
    ],
    "wallet_resolved": [
      {
        "raw": "worldcoin",
        "resolved": "worldcoin-wld",
        "via": "override"
      },
      {
        "raw": "pol",
        "resolved": "polygon-ecosystem-token",
        "via": "override"
      },
      {
        "raw": "bonk",
        "resolved": "bonk",
        "via": "id"
      },
      {
        "raw": "bome",
        "resolved": "book-of-meme",
        "via": "override"
      },
      {
        "raw": "official-trump",
        "resolved": "official-trump",
        "via": "id"
      },
      {
        "raw": "streamflow",
        "resolved": "streamflow",
        "via": "id"
      },
      {
        "raw": "pengu",
        "resolved": "pudgy-penguins",
        "via": "override"
      },
      {
        "raw": "just-a-chill-guy",
        "resolved": "just-a-chill-guy",
        "via": "id"
      },
      {
        "raw": "goatseus-maximus",
        "resolved": "goatseus-maximus",
        "via": "id"
      },
      {
        "raw": "optimism",
        "resolved": "optimism",
        "via": "id"
      },
      {
        "raw": "solana",
        "resolved": "solana",
        "via": "id"
      },
      {
        "raw": "ripple",
        "resolved": "ripple",
        "via": "id"
      }
    ],
    "missing": [],
    "ambiguous": []
  },
  "assets": {
    "BTC": {
      "usd": 122340,
      "change_24h": 1.7703626609178926,
      "change_7d": 11.623785295356297,
      "market_cap": 2438122924929,
      "id": "bitcoin",
      "name": "Bitcoin",
      "source": "coingecko"
    },
    "ETH": {
      "usd": 4492.23,
      "change_24h": 0.4494498128560725,
      "change_7d": 11.714620182820164,
      "market_cap": 542387798249,
      "id": "ethereum",
      "name": "Ethereum",
      "source": "coingecko"
    },
    "XRP": {
      "usd": 3,
      "change_24h": -1.7251279838989764,
      "change_7d": 7.270422939396318,
      "market_cap": 179685827406,
      "id": "ripple",
      "name": "XRP",
      "source": "coingecko"
    },
    "USDT": {
      "usd": 1,
      "change_24h": -0.021613732988492413,
      "change_7d": -0.011567947149537105,
      "market_cap": 176317818760,
      "id": "tether",
      "name": "Tether",
      "source": "coingecko"
    },
    "BNB": {
      "usd": 1156.58,
      "change_24h": 4.8470934899443785,
      "change_7d": 19.24841915954475,
      "market_cap": 161033149027,
      "id": "binancecoin",
      "name": "BNB",
      "source": "coingecko"
    },
    "SOL": {
      "usd": 228.92,
      "change_24h": -1.0168493071621088,
      "change_7d": 12.908940975343683,
      "market_cap": 124699726041,
      "id": "solana",
      "name": "Solana",
      "source": "coingecko"
    },
    "USDC": {
      "usd": 0.999712,
      "change_24h": 0.0006005989951638788,
      "change_7d": 0.0015077078477168172,
      "market_cap": 75377378442,
      "id": "usd-coin",
      "name": "USDC",
      "source": "coingecko"
    },
    "STETH": {
      "usd": 4488.88,
      "change_24h": 0.424764904933857,
      "change_7d": 11.69876335220116,
      "market_cap": 38270353133,
      "id": "staked-ether",
      "name": "Lido Staked Ether",
      "source": "coingecko"
    },
    "DOGE": {
      "usd": 0.252642,
      "change_24h": -1.2828423054693219,
      "change_7d": 9.009005619122043,
      "market_cap": 38194630153,
      "id": "dogecoin",
      "name": "Dogecoin",
      "source": "coingecko"
    },
    "TRX": {
      "usd": 0.340196,
      "change_24h": -0.6815287750542661,
      "change_7d": 0.7793799247045562,
      "market_cap": 32207300033,
      "id": "tron",
      "name": "TRON",
      "source": "coingecko"
    },
    "ADA": {
      "usd": 0.84775,
      "change_24h": -1.268053100540418,
      "change_7d": 7.225930556774964,
      "market_cap": 30972483000,
      "id": "cardano",
      "name": "Cardano",
      "source": "coingecko"
    },
    "WBTC": {
      "usd": 122137,
      "change_24h": 1.6780355444388935,
      "change_7d": 11.694832268033608,
      "market_cap": 15515972876,
      "id": "wrapped-bitcoin",
      "name": "Wrapped Bitcoin",
      "source": "coingecko"
    },
    "LINK": {
      "usd": 21.91,
      "change_24h": -2.1203212914275937,
      "change_7d": 4.221946280291406,
      "market_cap": 14858777932,
      "id": "chainlink",
      "name": "Chainlink",
      "source": "coingecko"
    },
    "AVAX": {
      "usd": 30.62,
      "change_24h": 0.9931753550434144,
      "change_7d": 6.342447463660121,
      "market_cap": 12917438725,
      "id": "avalanche-2",
      "name": "Avalanche",
      "source": "coingecko"
    },
    "XLM": {
      "usd": 0.398563,
      "change_24h": -1.6140138844296306,
      "change_7d": 10.16188064833633,
      "market_cap": 12739632668,
      "id": "stellar",
      "name": "Stellar",
      "source": "coingecko"
    },
    "BCH": {
      "usd": 588.85,
      "change_24h": -2.2494642649349963,
      "change_7d": 8.457142956178409,
      "market_cap": 11738552558,
      "id": "bitcoin-cash",
      "name": "Bitcoin Cash",
      "source": "coingecko"
    },
    "LTC": {
      "usd": 118.44,
      "change_24h": 1.3697276405400982,
      "change_7d": 14.020988604547751,
      "market_cap": 9044842736,
      "id": "litecoin",
      "name": "Litecoin",
      "source": "coingecko"
    },
    "LEO": {
      "usd": 9.63,
      "change_24h": 0.4957951739840515,
      "change_7d": 1.3455044975357071,
      "market_cap": 8884866893,
      "id": "leo-token",
      "name": "LEO Token",
      "source": "coingecko"
    },
    "SHIB": {
      "usd": 0.00001254,
      "change_24h": 0.7896507853629942,
      "change_7d": 5.4451252124739,
      "market_cap": 7385323600,
      "id": "shiba-inu",
      "name": "Shiba Inu",
      "source": "coingecko"
    },
    "DOT": {
      "usd": 4.24,
      "change_24h": 0.26082224609199633,
      "change_7d": 9.098215707854788,
      "market_cap": 6450157629,
      "id": "polkadot",
      "name": "Polkadot",
      "source": "coingecko"
    },
    "XMR": {
      "usd": 326.16,
      "change_24h": -1.8906057477753744,
      "change_7d": 13.104984494840096,
      "market_cap": 6017296430,
      "id": "monero",
      "name": "Monero",
      "source": "coingecko"
    },
    "OKB": {
      "usd": 233.73,
      "change_24h": 21.933003836877873,
      "change_7d": 22.890656560953467,
      "market_cap": 4908383467,
      "id": "okb",
      "name": "OKB",
      "source": "coingecko"
    },
    "UNI": {
      "usd": 8.02,
      "change_24h": -2.459145480837733,
      "change_7d": 6.233613747495589,
      "market_cap": 4817981488,
      "id": "uniswap",
      "name": "Uniswap",
      "source": "coingecko"
    },
    "DAI": {
      "usd": 0.998973,
      "change_24h": -0.10148294531177002,
      "change_7d": -0.10059756721126176,
      "market_cap": 4545995823,
      "id": "dai",
      "name": "Dai",
      "source": "coingecko"
    },
    "APT": {
      "usd": 5.4,
      "change_24h": 5.7674884314987205,
      "change_7d": 31.506017389935852,
      "market_cap": 3790492420,
      "id": "aptos",
      "name": "Aptos",
      "source": "coingecko"
    },
    "NEAR": {
      "usd": 2.96,
      "change_24h": 1.1943041654344453,
      "change_7d": 8.620441051623795,
      "market_cap": 3699821113,
      "id": "near",
      "name": "NEAR Protocol",
      "source": "coingecko"
    },
    "ETC": {
      "usd": 19.52,
      "change_24h": -0.9315275680025366,
      "change_7d": 7.249385884383649,
      "market_cap": 3001433910,
      "id": "ethereum-classic",
      "name": "Ethereum Classic",
      "source": "coingecko"
    },
    "WLD": {
      "usd": 1.29,
      "change_24h": -4.288756619486649,
      "change_7d": -1.43444889541869,
      "market_cap": 2792584045,
      "id": "worldcoin-wld",
      "name": "Worldcoin",
      "source": "coingecko"
    },
    "POL": {
      "usd": 0.236638,
      "change_24h": -0.7939323987091416,
      "change_7d": 5.655883729293093,
      "market_cap": 2487780661,
      "id": "polygon-ecosystem-token",
      "name": "POL (ex-MATIC)",
      "source": "coingecko"
    },
    "ICP": {
      "usd": 4.52,
      "change_24h": -0.567618921231997,
      "change_7d": 7.684635016472918,
      "market_cap": 2432136119,
      "id": "internet-computer",
      "name": "Internet Computer",
      "source": "coingecko"
    },
    "ARB": {
      "usd": 0.438435,
      "change_24h": -1.3565431579477938,
      "change_7d": 2.9529283342013204,
      "market_cap": 2367872414,
      "id": "arbitrum",
      "name": "Arbitrum",
      "source": "coingecko"
    },
    "KAS": {
      "usd": 0.077724,
      "change_24h": -1.6865926044401243,
      "change_7d": -0.5845720658282991,
      "market_cap": 2078845117,
      "id": "kaspa",
      "name": "Kaspa",
      "source": "coingecko"
    },
    "VET": {
      "usd": 0.02326126,
      "change_24h": -0.7323032367434765,
      "change_7d": 5.015142523244743,
      "market_cap": 2000127996,
      "id": "vechain",
      "name": "VeChain",
      "source": "coingecko"
    },
    "PENGU": {
      "usd": 0.03116563,
      "change_24h": 0.6607798350440193,
      "change_7d": 8.653248776199064,
      "market_cap": 1955430352,
      "id": "pudgy-penguins",
      "name": "Pudgy Penguins",
      "source": "coingecko"
    },
    "ALGO": {
      "usd": 0.22001,
      "change_24h": -1.580931767535652,
      "change_7d": 6.472103774100782,
      "market_cap": 1935271797,
      "id": "algorand",
      "name": "Algorand",
      "source": "coingecko"
    },
    "RENDER": {
      "usd": 3.51,
      "change_24h": -1.6113602778129037,
      "change_7d": 2.3558969540612913,
      "market_cap": 1820035316,
      "id": "render-token",
      "name": "Render",
      "source": "coingecko"
    },
    "SEI": {
      "usd": 0.291775,
      "change_24h": -0.4684514099326648,
      "change_7d": 3.95887305384601,
      "market_cap": 1788607669,
      "id": "sei-network",
      "name": "Sei",
      "source": "coingecko"
    },
    "FIL": {
      "usd": 2.34,
      "change_24h": 0.4090394892158099,
      "change_7d": 6.646093715189834,
      "market_cap": 1623628722,
      "id": "filecoin",
      "name": "Filecoin",
      "source": "coingecko"
    },
    "BONK": {
      "usd": 0.00002085,
      "change_24h": 4.279492648396897,
      "change_7d": 7.683987749921108,
      "market_cap": 1614455640,
      "id": "bonk",
      "name": "Bonk",
      "source": "coingecko"
    },
    "TRUMP": {
      "usd": 7.79,
      "change_24h": 0.039652902063532905,
      "change_7d": 2.836829688563474,
      "market_cap": 1557810086,
      "id": "official-trump",
      "name": "Official Trump",
      "source": "coingecko"
    },
    "IMX": {
      "usd": 0.765619,
      "change_24h": 8.349844429787398,
      "change_7d": 5.9919476462817505,
      "market_cap": 1484624334,
      "id": "immutable-x",
      "name": "Immutable",
      "source": "coingecko"
    },
    "OP": {
      "usd": 0.727606,
      "change_24h": -0.5638004617953213,
      "change_7d": 8.156612959083308,
      "market_cap": 1293755135,
      "id": "optimism",
      "name": "Optimism",
      "source": "coingecko"
    },
    "GRT": {
      "usd": 0.083721,
      "change_24h": -3.9240573007554023,
      "change_7d": 1.521083378310013,
      "market_cap": 880081790,
      "id": "the-graph",
      "name": "The Graph",
      "source": "coingecko"
    },
    "CFX": {
      "usd": 0.146075,
      "change_24h": -1.5001983184016772,
      "change_7d": 0.9485950729789363,
      "market_cap": 750941206,
      "id": "conflux-token",
      "name": "Conflux",
      "source": "coingecko"
    },
    "GALA": {
      "usd": 0.01592506,
      "change_24h": -0.17503964359284496,
      "change_7d": 8.783713547200739,
      "market_cap": 733360254,
      "id": "gala",
      "name": "GALA",
      "source": "coingecko"
    },
    "FLOW": {
      "usd": 0.375372,
      "change_24h": -0.4978606159865583,
      "change_7d": 7.248575787280956,
      "market_cap": 605588583,
      "id": "flow",
      "name": "Flow",
      "source": "coingecko"
    },
    "RUNE": {
      "usd": 1.19,
      "change_24h": -0.423404592159478,
      "change_7d": 5.067787237694687,
      "market_cap": 419488638,
      "id": "thorchain",
      "name": "THORChain",
      "source": "coingecko"
    },
    "FRAX": {
      "usd": 0.997801,
      "change_24h": -0.006657244829155981,
      "change_7d": -0.026584483223587065,
      "market_cap": 295467917,
      "id": "frax",
      "name": "Legacy Frax Dollar",
      "source": "coingecko"
    },
    "MINA": {
      "usd": 0.167015,
      "change_24h": 0.6318874412729926,
      "change_7d": 4.836893431170954,
      "market_cap": 209525897,
      "id": "mina-protocol",
      "name": "Mina Protocol",
      "source": "coingecko"
    },
    "BOME": {
      "usd": 0.0017741,
      "change_24h": 2.318809122236302,
      "change_7d": 7.714054818128221,
      "market_cap": 122382379,
      "id": "book-of-meme",
      "name": "BOOK OF MEME",
      "source": "coingecko"
    },
    "GOAT": {
      "usd": 0.088523,
      "change_24h": 2.1279113673874956,
      "change_7d": 9.519904188043135,
      "market_cap": 88516167,
      "id": "goatseus-maximus",
      "name": "Goatseus Maximus",
      "source": "coingecko"
    },
    "STREAM": {
      "usd": 0.062009,
      "change_24h": -0.7795288259942631,
      "change_7d": 7.863901609844154,
      "market_cap": 8429054,
      "id": "streamflow",
      "name": "Streamflow",
      "source": "coingecko"
    },
    "CHILLGUY": {
      "usd": 0.00024006,
      "change_24h": -2.6183858012744436,
      "change_7d": 5.5662380678618035,
      "market_cap": 240068,
      "id": "just-a-chill-guy",
      "name": "Just a chill guy (ETH)",
      "source": "coingecko"
    },
    "MKR": {
      "usd": 1637.14,
      "change_24h": -0.11147182577639467,
      "change_7d": 3.356722723529703,
      "market_cap": 0,
      "id": "maker",
      "name": "Maker",
      "source": "coingecko"
    },
    "FTM": {
      "usd": 0.278145,
      "change_24h": -0.6130355868517524,
      "change_7d": 15.466670740929715,
      "market_cap": 0,
      "id": "fantom",
      "name": "Fantom",
      "source": "coingecko"
    }
  }
}