{
  "updated_at": "2025-10-18T19:36:21.674Z",
  "meta": {
    "included_ids": [
      "bitcoin",
      "ethereum",
      "tether",
      "binancecoin",
      "solana",
      "ripple",
      "usd-coin",
      "staked-ether",
      "cardano",
      "dogecoin",
      "avalanche-2",
      "tron",
      "shiba-inu",
      "wrapped-bitcoin",
      "polkadot",
      "chainlink",
      "bitcoin-cash",
      "uniswap",
      "litecoin",
      "internet-computer",
      "dai",
      "near",
      "ethereum-classic",
      "filecoin",
      "aptos",
      "leo-token",
      "stellar",
      "okb",
      "vechain",
      "render-token",
      "monero",
      "arbitrum",
      "fantom",
      "the-graph",
      "immutable-x",
      "maker",
      "kaspa",
      "gala",
      "optimism",
      "frax",
      "sei-network",
      "algorand",
      "flow",
      "thorchain",
      "conflux-token",
      "mina-protocol",
      "worldcoin-wld",
      "polygon-ecosystem-token",
      "bonk",
      "book-of-meme",
      "official-trump",
      "streamflow",
      "pudgy-penguins",
      "just-a-chill-guy",
      "goatseus-maximus"
    ],
    "wallet_resolved": [
      {
        "raw": "worldcoin",
        "resolved": "worldcoin-wld",
        "via": "override"
      },
      {
        "raw": "pol",
        "resolved": "polygon-ecosystem-token",
        "via": "override"
      },
      {
        "raw": "bonk",
        "resolved": "bonk",
        "via": "id"
      },
      {
        "raw": "bome",
        "resolved": "book-of-meme",
        "via": "override"
      },
      {
        "raw": "official-trump",
        "resolved": "official-trump",
        "via": "id"
      },
      {
        "raw": "streamflow",
        "resolved": "streamflow",
        "via": "id"
      },
      {
        "raw": "pengu",
        "resolved": "pudgy-penguins",
        "via": "override"
      },
      {
        "raw": "just-a-chill-guy",
        "resolved": "just-a-chill-guy",
        "via": "id"
      },
      {
        "raw": "goatseus-maximus",
        "resolved": "goatseus-maximus",
        "via": "id"
      },
      {
        "raw": "optimism",
        "resolved": "optimism",
        "via": "id"
      },
      {
        "raw": "solana",
        "resolved": "solana",
        "via": "id"
      },
      {
        "raw": "ripple",
        "resolved": "ripple",
        "via": "id"
      }
    ],
    "missing": [],
    "ambiguous": []
  },
  "assets": {
    "BTC": {
      "usd": 106997,
      "change_24h": 0.5658995626567374,
      "change_7d": -4.494493790285197,
      "market_cap": 2133229508421,
      "id": "bitcoin",
      "name": "Bitcoin",
      "source": "coingecko"
    },
    "ETH": {
      "usd": 3889.75,
      "change_24h": 1.7159184731586126,
      "change_7d": 1.559771206741726,
      "market_cap": 469547126680,
      "id": "ethereum",
      "name": "Ethereum",
      "source": "coingecko"
    },
    "USDT": {
      "usd": 1.001,
      "change_24h": 0.006496741338356621,
      "change_7d": -0.07708947764001794,
      "market_cap": 181786582859,
      "id": "tether",
      "name": "Tether",
      "source": "coingecko"
    },
    "BNB": {
      "usd": 1100.37,
      "change_24h": 2.9500082017041356,
      "change_7d": -6.715432925332693,
      "market_cap": 153184246586,
      "id": "binancecoin",
      "name": "BNB",
      "source": "coingecko"
    },
    "XRP": {
      "usd": 2.37,
      "change_24h": 2.782050454838191,
      "change_7d": -4.647386144485185,
      "market_cap": 142000560164,
      "id": "ripple",
      "name": "XRP",
      "source": "coingecko"
    },
    "SOL": {
      "usd": 185.99,
      "change_24h": 2.090322989939476,
      "change_7d": 1.68550404960825,
      "market_cap": 101717500338,
      "id": "solana",
      "name": "Solana",
      "source": "coingecko"
    },
    "USDC": {
      "usd": 0.999905,
      "change_24h": 0.007002054823809048,
      "change_7d": 0.0004672308368225156,
      "market_cap": 75947567647,
      "id": "usd-coin",
      "name": "USDC",
      "source": "coingecko"
    },
    "STETH": {
      "usd": 3886.44,
      "change_24h": 1.7702612568277678,
      "change_7d": 1.663168422789567,
      "market_cap": 33006436974,
      "id": "staked-ether",
      "name": "Lido Staked Ether",
      "source": "coingecko"
    },
    "TRX": {
      "usd": 0.314602,
      "change_24h": 2.109912926495874,
      "change_7d": -1.662057962845741,
      "market_cap": 29776290758,
      "id": "tron",
      "name": "TRON",
      "source": "coingecko"
    },
    "DOGE": {
      "usd": 0.189464,
      "change_24h": 2.6732043606521647,
      "change_7d": -1.9190088570812152,
      "market_cap": 28677437124,
      "id": "dogecoin",
      "name": "Dogecoin",
      "source": "coingecko"
    },
    "ADA": {
      "usd": 0.636023,
      "change_24h": 1.9744629911141387,
      "change_7d": -3.1806335727217667,
      "market_cap": 23254960330,
      "id": "cardano",
      "name": "Cardano",
      "source": "coingecko"
    },
    "WBTC": {
      "usd": 107023,
      "change_24h": 0.5583088814468,
      "change_7d": -4.484785259469557,
      "market_cap": 13589658650,
      "id": "wrapped-bitcoin",
      "name": "Wrapped Bitcoin",
      "source": "coingecko"
    },
    "LINK": {
      "usd": 16.84,
      "change_24h": 3.235392934648065,
      "change_7d": -6.021997759207994,
      "market_cap": 11735949245,
      "id": "chainlink",
      "name": "Chainlink",
      "source": "coingecko"
    },
    "XLM": {
      "usd": 0.317513,
      "change_24h": 3.498820660470235,
      "change_7d": -3.96444314563016,
      "market_cap": 10159653857,
      "id": "stellar",
      "name": "Stellar",
      "source": "coingecko"
    },
    "BCH": {
      "usd": 467.13,
      "change_24h": 0.43723748680480257,
      "change_7d": -10.658035129204556,
      "market_cap": 9316587417,
      "id": "bitcoin-cash",
      "name": "Bitcoin Cash",
      "source": "coingecko"
    },
    "LEO": {
      "usd": 9.4,
      "change_24h": -0.3898076628541324,
      "change_7d": -2.443897018129728,
      "market_cap": 8677138922,
      "id": "leo-token",
      "name": "LEO Token",
      "source": "coingecko"
    },
    "AVAX": {
      "usd": 20.15,
      "change_24h": 1.405969089361794,
      "change_7d": -12.290861273032377,
      "market_cap": 8592065301,
      "id": "avalanche-2",
      "name": "Avalanche",
      "source": "coingecko"
    },
    "LTC": {
      "usd": 91.97,
      "change_24h": 1.6565893378592809,
      "change_7d": -5.473260416394133,
      "market_cap": 7027977763,
      "id": "litecoin",
      "name": "Litecoin",
      "source": "coingecko"
    },
    "SHIB": {
      "usd": 0.00000991,
      "change_24h": 2.2053815412185584,
      "change_7d": -3.879198616318164,
      "market_cap": 5837468076,
      "id": "shiba-inu",
      "name": "Shiba Inu",
      "source": "coingecko"
    },
    "XMR": {
      "usd": 310.19,
      "change_24h": 7.901021431253979,
      "change_7d": 1.9712348433586424,
      "market_cap": 5707353320,
      "id": "monero",
      "name": "Monero",
      "source": "coingecko"
    },
    "DAI": {
      "usd": 1,
      "change_24h": 0.03490698619843506,
      "change_7d": 0.03965905545733043,
      "market_cap": 4602750125,
      "id": "dai",
      "name": "Dai",
      "source": "coingecko"
    },
    "DOT": {
      "usd": 2.93,
      "change_24h": 1.1015533370698616,
      "change_7d": -6.510815226870395,
      "market_cap": 4464951838,
      "id": "polkadot",
      "name": "Polkadot",
      "source": "coingecko"
    },
    "UNI": {
      "usd": 6.04,
      "change_24h": -1.4828826005174442,
      "change_7d": -0.7737272979166627,
      "market_cap": 3628260085,
      "id": "uniswap",
      "name": "Uniswap",
      "source": "coingecko"
    },
    "OKB": {
      "usd": 168.68,
      "change_24h": 3.0536629794438057,
      "change_7d": -6.171375951693632,
      "market_cap": 3542453366,
      "id": "okb",
      "name": "OKB",
      "source": "coingecko"
    },
    "NEAR": {
      "usd": 2.15,
      "change_24h": 0.535507553981356,
      "change_7d": -9.6168488013559,
      "market_cap": 2690045480,
      "id": "near",
      "name": "NEAR Protocol",
      "source": "coingecko"
    },
    "ETC": {
      "usd": 15.41,
      "change_24h": 0.3210585122909994,
      "change_7d": 0.7576156998416796,
      "market_cap": 2373304695,
      "id": "ethereum-classic",
      "name": "Ethereum Classic",
      "source": "coingecko"
    },
    "APT": {
      "usd": 3.2,
      "change_24h": 0.7328023540961148,
      "change_7d": -16.046975527899882,
      "market_cap": 2300987192,
      "id": "aptos",
      "name": "Aptos",
      "source": "coingecko"
    },
    "POL": {
      "usd": 0.188388,
      "change_24h": 1.388903685298357,
      "change_7d": -1.859229898097049,
      "market_cap": 1981775445,
      "id": "polygon-ecosystem-token",
      "name": "POL (ex-MATIC)",
      "source": "coingecko"
    },
    "WLD": {
      "usd": 0.889264,
      "change_24h": 2.201026384332229,
      "change_7d": -3.910703068773866,
      "market_cap": 1973216792,
      "id": "worldcoin-wld",
      "name": "Worldcoin",
      "source": "coingecko"
    },
    "ARB": {
      "usd": 0.308858,
      "change_24h": 1.7718892738057754,
      "change_7d": -3.6991236799718843,
      "market_cap": 1701796307,
      "id": "arbitrum",
      "name": "Arbitrum",
      "source": "coingecko"
    },
    "ICP": {
      "usd": 3.06,
      "change_24h": 2.971197469221818,
      "change_7d": -6.359728278913103,
      "market_cap": 1651409273,
      "id": "internet-computer",
      "name": "Internet Computer",
      "source": "coingecko"
    },
    "ALGO": {
      "usd": 0.180412,
      "change_24h": 2.0920483747994623,
      "change_7d": -5.215264079114359,
      "market_cap": 1590020116,
      "id": "algorand",
      "name": "Algorand",
      "source": "coingecko"
    },
    "VET": {
      "usd": 0.01713251,
      "change_24h": 0.4540545463770165,
      "change_7d": -1.0870711556997208,
      "market_cap": 1473058603,
      "id": "vechain",
      "name": "VeChain",
      "source": "coingecko"
    },
    "KAS": {
      "usd": 0.050482,
      "change_24h": -1.783678451032157,
      "change_7d": -15.033552923890392,
      "market_cap": 1351596294,
      "id": "kaspa",
      "name": "Kaspa",
      "source": "coingecko"
    },
    "PENGU": {
      "usd": 0.02136976,
      "change_24h": 2.4561809035662368,
      "change_7d": -6.0683480555537965,
      "market_cap": 1344441442,
      "id": "pudgy-penguins",
      "name": "Pudgy Penguins",
      "source": "coingecko"
    },
    "RENDER": {
      "usd": 2.48,
      "change_24h": 1.6135487738974774,
      "change_7d": 0.13549683376133634,
      "market_cap": 1283725456,
      "id": "render-token",
      "name": "Render",
      "source": "coingecko"
    },
    "SEI": {
      "usd": 0.192271,
      "change_24h": 0.6174253887292045,
      "change_7d": -12.03629577790352,
      "market_cap": 1201394911,
      "id": "sei-network",
      "name": "Sei",
      "source": "coingecko"
    },
    "TRUMP": {
      "usd": 5.89,
      "change_24h": 2.5066399327970226,
      "change_7d": -1.4445612794156537,
      "market_cap": 1178469481,
      "id": "official-trump",
      "name": "Official Trump",
      "source": "coingecko"
    },
    "BONK": {
      "usd": 0.00001421,
      "change_24h": 2.9306623888651546,
      "change_7d": -0.48613406284276073,
      "market_cap": 1099894121,
      "id": "bonk",
      "name": "Bonk",
      "source": "coingecko"
    },
    "FIL": {
      "usd": 1.49,
      "change_24h": 2.4128085122786818,
      "change_7d": -9.478896430173233,
      "market_cap": 1045902781,
      "id": "filecoin",
      "name": "Filecoin",
      "source": "coingecko"
    },
    "IMX": {
      "usd": 0.496409,
      "change_24h": 0.5094090659466436,
      "change_7d": -1.4490260531189905,
      "market_cap": 962935144,
      "id": "immutable-x",
      "name": "Immutable",
      "source": "coingecko"
    },
    "OP": {
      "usd": 0.425765,
      "change_24h": 1.791000596566341,
      "change_7d": -11.410904793843653,
      "market_cap": 757240053,
      "id": "optimism",
      "name": "Optimism",
      "source": "coingecko"
    },
    "GRT": {
      "usd": 0.062695,
      "change_24h": 0.5230153640800432,
      "change_7d": -4.787818013866995,
      "market_cap": 661623681,
      "id": "the-graph",
      "name": "The Graph",
      "source": "coingecko"
    },
    "CFX": {
      "usd": 0.110149,
      "change_24h": 3.5261365561905276,
      "change_7d": 6.200850770420434,
      "market_cap": 566668239,
      "id": "conflux-token",
      "name": "Conflux",
      "source": "coingecko"
    },
    "GALA": {
      "usd": 0.01094822,
      "change_24h": 2.784118830275437,
      "change_7d": -0.3003671763692548,
      "market_cap": 506361571,
      "id": "gala",
      "name": "GALA",
      "source": "coingecko"
    },
    "FLOW": {
      "usd": 0.269141,
      "change_24h": 0.5677327522965993,
      "change_7d": -2.6890464349450944,
      "market_cap": 435062793,
      "id": "flow",
      "name": "Flow",
      "source": "coingecko"
    },
    "FRAX": {
      "usd": 0.997058,
      "change_24h": 0.10395789351678272,
      "change_7d": -0.028949712217444058,
      "market_cap": 295292841,
      "id": "frax",
      "name": "Legacy Frax Dollar",
      "source": "coingecko"
    },
    "RUNE": {
      "usd": 0.838399,
      "change_24h": 0.19234110809452623,
      "change_7d": -6.237196105536804,
      "market_cap": 294461803,
      "id": "thorchain",
      "name": "THORChain",
      "source": "coingecko"
    },
    "MINA": {
      "usd": 0.109466,
      "change_24h": 1.8881479249788415,
      "change_7d": -5.61898573623362,
      "market_cap": 137641605,
      "id": "mina-protocol",
      "name": "Mina Protocol",
      "source": "coingecko"
    },
    "BOME": {
      "usd": 0.00105945,
      "change_24h": 2.9712440399911966,
      "change_7d": -1.3610059057030526,
      "market_cap": 73089387,
      "id": "book-of-meme",
      "name": "BOOK OF MEME",
      "source": "coingecko"
    },
    "GOAT": {
      "usd": 0.052537,
      "change_24h": 1.8173680916686168,
      "change_7d": -10.379452938196247,
      "market_cap": 52513393,
      "id": "goatseus-maximus",
      "name": "Goatseus Maximus",
      "source": "coingecko"
    },
    "STREAM": {
      "usd": 0.035779,
      "change_24h": -1.456594476912266,
      "change_7d": -40.24219681481569,
      "market_cap": 4867207,
      "id": "streamflow",
      "name": "Streamflow",
      "source": "coingecko"
    },
    "CHILLGUY": {
      "usd": 0.00018195,
      "change_24h": 1.8200251430786814,
      "change_7d": -0.8975819425683778,
      "market_cap": 181951,
      "id": "just-a-chill-guy",
      "name": "Just a chill guy (ETH)",
      "source": "coingecko"
    },
    "MKR": {
      "usd": 1398.26,
      "change_24h": -1.5849504270019126,
      "change_7d": -0.30860466820772486,
      "market_cap": 0,
      "id": "maker",
      "name": "Maker",
      "source": "coingecko"
    },
    "FTM": {
      "usd": 0.174489,
      "change_24h": -0.41016797688578815,
      "change_7d": -11.821695663991601,
      "market_cap": 0,
      "id": "fantom",
      "name": "Fantom",
      "source": "coingecko"
    }
  }
}